wppcpy/__init__.py
wppcpy/filesystem.py
wppcpy/constraints/__init__.py
wppcpy/constraints/base.py
wppcpy/constraints/file.py
wppcpy/constraints/header.py
wppcpy/exceptions/__init__.py
wppcpy/exceptions/base.py
wppcpy/exceptions/file.py
wppcpy-0.1.1.dist-info/METADATA
wppcpy-0.1.1.dist-info/WHEEL
wppcpy-0.1.1.dist-info/top_level.txt
wppcpy-0.1.1.dist-info/RECORD
