Metadata-Version: 2.1
Name: wppcpy
Version: 0.1.1
Summary: Verify that the directory is a WordPress plugin based on the defined constraints.
Home-page: https://github.com/shahmal1yev
Author: shahmal1yev
License: MIT
